devtools_cidr/__init__.py
devtools_cidr-1.0.1.dist-info/METADATA
devtools_cidr-1.0.1.dist-info/WHEEL
devtools_cidr-1.0.1.dist-info/top_level.txt
devtools_cidr-1.0.1.dist-info/RECORD
