Metadata-Version: 2.1
Name: devtools-cidr
Version: 1.0.1
Summary: CIDR notation calculator
Home-page: https://devtools.at/tools/cidr-calculator
Author: DevTools.at
Author-email: hello@devtools.at
Project-URL: Homepage, https://devtools.at/tools/cidr-calculator
Project-URL: Repository, https://github.com/devtools-at/cidr-calculator
Classifier: Development Status :: 4 - Beta
Classifier: Intended Audience :: Developers
Classifier: License :: OSI Approved :: MIT License
Classifier: Programming Language :: Python :: 3
Requires-Python: >=3.8
